hunterdouglasplatinum/__init__.py
hunterdouglasplatinum/__main__.py
hunterdouglasplatinum/hunterdouglasplatinum.py
pyhunterdouglasplatinum-2.0.0.dist-info/LICENSE
pyhunterdouglasplatinum-2.0.0.dist-info/METADATA
pyhunterdouglasplatinum-2.0.0.dist-info/WHEEL
pyhunterdouglasplatinum-2.0.0.dist-info/entry_points.txt
pyhunterdouglasplatinum-2.0.0.dist-info/top_level.txt
pyhunterdouglasplatinum-2.0.0.dist-info/RECORD
