Metadata-Version: 2.1
Name: pyhunterdouglasplatinum
Version: 2.0.0
Summary: Python library to talk to Hunter Douglas Platinum Hubs
Home-page: https://github.com/schwark/pyhunterdouglasplatinum
Author: Schwark Satyavolu
Author-email: schwark@alum.rpi.edu
License: MIT
Platform: UNKNOWN
Classifier: License :: OSI Approved :: MIT License
Classifier: Programming Language :: Python :: 3
Classifier: Programming Language :: Python :: 3.8
